image_processing/__init__.py
image_processing/file1_name.py
image_processing/file2_name.py
image_processing_test_hg-0.0.1.dist-info/METADATA
image_processing_test_hg-0.0.1.dist-info/WHEEL
image_processing_test_hg-0.0.1.dist-info/top_level.txt
image_processing_test_hg-0.0.1.dist-info/RECORD
