Metadata-Version: 2.1
Name: image-processing-test-hg
Version: 0.0.1
Summary: Passo a passo passado por Karina Kato.
Home-page: https://github.com/htonioni/image-processing-package
Author: Hugo
Requires-Python: >=3.8
